automatedweb.py
automatedweb-1.0.1.dist-info/LICENSE
automatedweb-1.0.1.dist-info/METADATA
automatedweb-1.0.1.dist-info/WHEEL
automatedweb-1.0.1.dist-info/top_level.txt
automatedweb-1.0.1.dist-info/RECORD
