Metadata-Version: 2.1
Name: automatedweb
Version: 1.0.1
Summary: A tool to make it easy to communicate with web systems writting and reading data from them
Home-page: https://github.com/renanleonellocastro/automatedweb.git
Author: Renan Leonello Castro
Author-email: renanleonellocastro@gmail.com
License: MIT License
Keywords: automatedweb web automated post get requests rest restfull
Platform: UNKNOWN
Classifier: Programming Language :: Python :: 3
Classifier: Operating System :: OS Independent
Requires-Dist: requests (>=2.22.0)
Requires-Dist: pyquery (>=1.4.0)
Requires-Dist: json5 (>=0.8.5)
Requires-Dist: urllib3 (>=1.25.10)
